src/__init__.py
src/entities/__init__.py
src/entities/config.py
src/entities/endpoint_settings.py
src/entities/model_settings.py
src/entities/pagination.py
src/implementations/__init__.py
src/implementations/builders/__init__.py
src/implementations/builders/api.py
src/implementations/builders/crud.py
src/implementations/builders/endpoint.py
src/implementations/builders/model.py
src/implementations/storages/__init__.py
src/implementations/storages/exceptions.py
src/implementations/storages/postgres/__init__.py
src/implementations/storages/postgres/base.py
src/implementations/storages/postgres/manager.py
src/interfaces/__init__.py
src/interfaces/builders/__init__.py
src/interfaces/builders/api.py
src/interfaces/builders/crud.py
src/interfaces/builders/endpoint.py
src/interfaces/builders/model.py
src/interfaces/storages/__init__.py
src/interfaces/storages/base.py
src/interfaces/storages/manager.py
dynoapi-0.1.0.dist-info/METADATA
dynoapi-0.1.0.dist-info/WHEEL
dynoapi-0.1.0.dist-info/RECORD
