Metadata-Version: 2.1
Name: dynoapi
Version: 0.1.0
Summary: 
Author: Artem Bogdanov
Author-email: abogdaov@gmail.com
Requires-Python: >=3.11,<4.0
Classifier: Programming Language :: Python :: 3
Classifier: Programming Language :: Python :: 3.11
Classifier: Programming Language :: Python :: 3.12
Requires-Dist: fastapi (>=0.110.0,<0.111.0)
Requires-Dist: pydantic (>=2.6.4,<3.0.0)
